eloguru
