Metadata-Version: 2.1
Name: eloguru
Version: 0.0.2
Summary: 带发邮件的loguru包装，支持全部loguru功能和邮件发送功能
Home-page: https://github.com/425776024/eloguru
Author: Jiang.XinFa
Author-email: 425776024@qq.com
License: MIT Licence
Keywords: email,log,loguru,日志邮件
Platform: any
